projectedlmc/__init__.py
projectedlmc/projected_lmc.py
projectedlmc-0.0.7.dist-info/LICENSE
projectedlmc-0.0.7.dist-info/METADATA
projectedlmc-0.0.7.dist-info/WHEEL
projectedlmc-0.0.7.dist-info/top_level.txt
projectedlmc-0.0.7.dist-info/RECORD
