Metadata-Version: 2.1
Name: projectedlmc
Version: 0.0.7
Summary: A short package based on gpytorch implementing the Projected LMC model
Home-page: https://qwerty6191.github.io/projected-lmc/
Author: 
Author-email: 
Classifier: Programming Language :: Python :: 3
Classifier: License :: OSI Approved :: MIT License
Classifier: Operating System :: OS Independent
Requires-Python: >=3.7
License-File: LICENSE
Requires-Dist: gpytorch
Requires-Dist: linear-operator
Requires-Dist: scikit-learn
